ordbok/__init__.py
ordbok/cli.py
ordbok/config_env.py
ordbok/config_file.py
ordbok/config_private.py
ordbok/console.py
ordbok/exceptions.py
ordbok/flask_helper.py
ordbok/ordbok.py
ordbok/private.py
ordbok/util.py
ordbok-0.1.9.dist-info/DESCRIPTION.rst
ordbok-0.1.9.dist-info/entry_points.txt
ordbok-0.1.9.dist-info/METADATA
ordbok-0.1.9.dist-info/metadata.json
ordbok-0.1.9.dist-info/RECORD
ordbok-0.1.9.dist-info/top_level.txt
ordbok-0.1.9.dist-info/WHEEL
