Metadata-Version: 2.0
Name: ordbok
Version: 0.1.9
Summary: Bring order to the chaos of configuration.
Home-page: http://github.com/eriktaubeneck/ordbok
Author: Erik Taubeneck
Author-email: erik.taubeneck@gmail.com
License: MIT
Platform: any
Classifier: Development Status :: 3 - Alpha
Classifier: Environment :: Plugins
Classifier: Environment :: Web Environment
Classifier: Framework :: Flask
Classifier: Intended Audience :: Developers
Classifier: License :: OSI Approved :: MIT License
Classifier: Natural Language :: English 
Classifier: Operating System :: OS Independent
Classifier: Programming Language :: Python :: 2
Classifier: Programming Language :: Python :: 3
Classifier: Topic :: Software Development :: Build Tools
Classifier: Topic :: Software Development :: Libraries :: Python Modules
Requires-Dist: pyyaml (>=3.0,<4.a0)
Requires-Dist: six (>=1.9.0,<2.a0)
Requires-Dist: simple-crypt (>=4.0.0,<5.a0)
